{"@context":{"@language":"en","@vocab":"https://schema.org/","citeAs":"cr:citeAs","column":"cr:column","conformsTo":"dct:conformsTo","cr":"http://mlcommons.org/croissant/","data":{"@id":"cr:data","@type":"@json"},"dataBiases":"cr:dataBiases","dataCollection":"cr:dataCollection","dataType":{"@id":"cr:dataType","@type":"@vocab"},"dct":"http://purl.org/dc/terms/","extract":"cr:extract","field":"cr:field","fileProperty":"cr:fileProperty","fileObject":"cr:fileObject","fileSet":"cr:fileSet","format":"cr:format","includes":"cr:includes","isEnumeration":"cr:isEnumeration","isLiveDataset":"cr:isLiveDataset","jsonPath":"cr:jsonPath","key":"cr:key","md5":"cr:md5","parentField":"cr:parentField","path":"cr:path","personalSensitiveInformation":"cr:personalSensitiveInformation","recordSet":"cr:recordSet","references":"cr:references","regex":"cr:regex","repeated":"cr:repeated","replace":"cr:replace","sc":"https://schema.org/","separator":"cr:separator","source":"cr:source","subField":"cr:subField","transform":"cr:transform","wd":"https://www.wikidata.org/wiki/"},"alternateName":"Measuring air pollution particulates in Vauxhall","conformsTo":"http://mlcommons.org/croissant/1.0","license":{"@type":"sc:CreativeWork","name":"Unknown"},"distribution":[{"contentUrl":"https://www.kaggle.com/api/v1/datasets/download/annarobinette/london-air-quality-at-bondway-interchange-lambeth","contentSize":"1.191 MB","encodingFormat":"application/zip","@id":"archive.zip","@type":"cr:FileObject","name":"archive.zip","description":"Archive containing all the contents of the London Air Quality at Bondway Interchange, Lambeth dataset"},{"contentUrl":"AirQualityData_LambethBondway_2018-2023.csv","containedIn":{"@id":"archive.zip"},"encodingFormat":"text/csv","@id":"AirQualityData_LambethBondway_2018-2023.csv_fileobject","@type":"cr:FileObject","name":"AirQualityData_LambethBondway_2018-2023.csv"},{"contentUrl":"AirQualityData_LambethBondway_2019-2022.csv","containedIn":{"@id":"archive.zip"},"encodingFormat":"text/csv","@id":"AirQualityData_LambethBondway_2019-2022.csv_fileobject","@type":"cr:FileObject","name":"AirQualityData_LambethBondway_2019-2022.csv"},{"contentUrl":"WHO_AQG.csv","containedIn":{"@id":"archive.zip"},"encodingFormat":"text/csv","@id":"WHO_AQG.csv_fileobject","@type":"cr:FileObject","name":"WHO_AQG.csv"}],"recordSet":[{"field":[{"dataType":["sc:Text"],"source":{"fileObject":{"@id":"AirQualityData_LambethBondway_2018-2023.csv_fileobject"},"extract":{"column":"Site"}},"@id":"AirQualityData_LambethBondway_2018-2023.csv/Site","@type":"cr:Field","name":"Site"},{"dataType":["sc:Text"],"source":{"fileObject":{"@id":"AirQualityData_LambethBondway_2018-2023.csv_fileobject"},"extract":{"column":"Species"}},"@id":"AirQualityData_LambethBondway_2018-2023.csv/Species","@type":"cr:Field","name":"Species"},{"dataType":["sc:Text"],"source":{"fileObject":{"@id":"AirQualityData_LambethBondway_2018-2023.csv_fileobject"},"extract":{"column":"ReadingDateTime"}},"@id":"AirQualityData_LambethBondway_2018-2023.csv/ReadingDateTime","@type":"cr:Field","name":"ReadingDateTime"},{"dataType":["sc:Float"],"source":{"fileObject":{"@id":"AirQualityData_LambethBondway_2018-2023.csv_fileobject"},"extract":{"column":"Value"}},"@id":"AirQualityData_LambethBondway_2018-2023.csv/Value","@type":"cr:Field","name":"Value"},{"dataType":["sc:Text"],"source":{"fileObject":{"@id":"AirQualityData_LambethBondway_2018-2023.csv_fileobject"},"extract":{"column":"Units"}},"@id":"AirQualityData_LambethBondway_2018-2023.csv/Units","@type":"cr:Field","name":"Units"},{"dataType":["sc:Text"],"source":{"fileObject":{"@id":"AirQualityData_LambethBondway_2018-2023.csv_fileobject"},"extract":{"column":"Provisional or Ratified"}},"@id":"AirQualityData_LambethBondway_2018-2023.csv/Provisional\u002Bor\u002BRatified","@type":"cr:Field","name":"Provisional or Ratified"}],"@id":"AirQualityData_LambethBondway_2018-2023.csv","@type":"cr:RecordSet","name":"AirQualityData_LambethBondway_2018-2023.csv"},{"field":[{"dataType":["sc:Text"],"source":{"fileObject":{"@id":"AirQualityData_LambethBondway_2019-2022.csv_fileobject"},"extract":{"column":"Site"}},"@id":"AirQualityData_LambethBondway_2019-2022.csv/Site","@type":"cr:Field","name":"Site"},{"dataType":["sc:Boolean"],"source":{"fileObject":{"@id":"AirQualityData_LambethBondway_2019-2022.csv_fileobject"},"extract":{"column":"Species"}},"@id":"AirQualityData_LambethBondway_2019-2022.csv/Species","@type":"cr:Field","name":"Species"},{"dataType":["sc:Text"],"source":{"fileObject":{"@id":"AirQualityData_LambethBondway_2019-2022.csv_fileobject"},"extract":{"column":"ReadingDateTime"}},"@id":"AirQualityData_LambethBondway_2019-2022.csv/ReadingDateTime","@type":"cr:Field","name":"ReadingDateTime"},{"dataType":["sc:Float"],"source":{"fileObject":{"@id":"AirQualityData_LambethBondway_2019-2022.csv_fileobject"},"extract":{"column":"Value"}},"@id":"AirQualityData_LambethBondway_2019-2022.csv/Value","@type":"cr:Field","name":"Value"},{"dataType":["sc:Text"],"source":{"fileObject":{"@id":"AirQualityData_LambethBondway_2019-2022.csv_fileobject"},"extract":{"column":"Units"}},"@id":"AirQualityData_LambethBondway_2019-2022.csv/Units","@type":"cr:Field","name":"Units"},{"dataType":["sc:Text"],"source":{"fileObject":{"@id":"AirQualityData_LambethBondway_2019-2022.csv_fileobject"},"extract":{"column":"Provisional or Ratified"}},"@id":"AirQualityData_LambethBondway_2019-2022.csv/Provisional\u002Bor\u002BRatified","@type":"cr:Field","name":"Provisional or Ratified"}],"@id":"AirQualityData_LambethBondway_2019-2022.csv","@type":"cr:RecordSet","name":"AirQualityData_LambethBondway_2019-2022.csv"},{"field":[{"dataType":["sc:Text"],"source":{"fileObject":{"@id":"WHO_AQG.csv_fileobject"},"extract":{"column":""}},"@id":"WHO_AQG.csv/","@type":"cr:Field","name":""},{"dataType":["sc:Text"],"source":{"fileObject":{"@id":"WHO_AQG.csv_fileobject"},"extract":{"column":""}},"@id":"WHO_AQG.csv/","@type":"cr:Field","name":""},{"dataType":["sc:Text"],"source":{"fileObject":{"@id":"WHO_AQG.csv_fileobject"},"extract":{"column":""}},"@id":"WHO_AQG.csv/","@type":"cr:Field","name":""}],"@id":"WHO_AQG.csv","@type":"cr:RecordSet","name":"WHO_AQG.csv"}],"keywords":["data type \u003E tabular","subject \u003E earth and nature \u003E environment \u003E pollution","subject \u003E health and fitness \u003E health \u003E public health","technique \u003E exploratory data analysis","geography and places \u003E europe"],"isAccessibleForFree":true,"isLiveDataset":true,"includedInDataCatalog":{"@type":"sc:DataCatalog","name":"Kaggle","url":"https://www.kaggle.com"},"creator":{"@type":"sc:Person","name":"Anna Robinette","url":"/annarobinette","image":"https://storage.googleapis.com/kaggle-avatars/thumbnails/default-thumb.png"},"publisher":{"@type":"sc:Organization","name":"Kaggle","url":"https://www.kaggle.com/organizations/kaggle","image":"https://storage.googleapis.com/kaggle-organizations/4/thumbnail.png"},"thumbnailUrl":"https://storage.googleapis.com/kaggle-datasets-images/4402961/7561566/4373091b75b2be821ba21a39c70d881f/dataset-card.jpeg?t=2024-02-05-12-28-40","dateModified":"2024-02-05T16:24:39.327","datePublished":"2024-02-05T12:20:05.587","@type":"sc:Dataset","name":"London Air Quality at Bondway Interchange, Lambeth","url":"https://www.kaggle.com/datasets/annarobinette/london-air-quality-at-bondway-interchange-lambeth","description":"Specific data from the Bond Interchange near Vauxhall in London measuring Nitric Oxide (ug/m3), Nitrogen Dioxide (ug/m3), Oxides of Nitrogen (ug/m3 as NO2), PM10 Particulate (by BAMH) (ug/m3), Sulphur Dioxide (ug/m3).\n\nThe dates of years 2019 \u2013 2022 overlap with the introduction of the original ULEZ area in October 2021, for which the data site is on the border.\n\nFrom [London Air](https://www.londonair.org.uk/LondonAir/General/about.aspx)\n\n\u0022#What is londonair?\n- Londonair is the website of the London Air Quality Network (LAQN), and shows air pollution in London and south east England.\n- The website provides information for the public, for policy users, and for scientists.\n- The LAQN was formed in 1993 to coordinate and improve air pollution monitoring in London.\n- The network provides independent scientific measurements and assessment.\n- Establishing and running a monitoring site requires a large investment, and it is not possible to put monitoring everywhere, so we have developed maps and models to predict the pollution levels in between.\n#Why is it needed?\n- Air pollution is a very large public health issue in London.\n- The measurements are used to assess air pollution across London, and to track trends over time.\n- These measurements are used to create models that can assess how different government policies affect air pollution.\n- The measurements help fulfil the local authorities statutory obligations with regard to air pollution.\n- The measurements are also used to help with research into the health effects of air pollution.\n#Who provides Londonair?\n- Londonair is provided by the Environmental Research Group of Imperial College London.\n- Each individual partner organisation in the LAQN contributes to funding the management and coordination.\n- The monitoring is owned and funded by local authorities, Business Improvement Districts (BIDs), TfL and Defra. We support them in choosing the location to best answer the question posed, but the decision to establish a monitoring site lies with them.\n- Increasingly LAQN information from within London is being enhanced with measurements from surrounding local authority members, who are often impacted by London emissions.\u0022"}